{
  "timestamp": "2026-07-22T20:48:34.629566+00:00",
  "generatedAt": "2026-07-22T20:48:34.629566+00:00",
  "data": [
    {
      "id": "tai",
      "symbol": "^TWII",
      "name": "加權指數 TAIEX",
      "region": "TW",
      "currency": "NT$",
      "price": 44825.78,
      "change": 592.91,
      "changePct": 1.34,
      "asOf": "2026-07-22T05:33:00+00:00",
      "source": "TWSE MIS",
      "priceType": "trade"
    },
    {
      "id": "otc",
      "symbol": "^TWOII",
      "name": "OTC 櫃買指數",
      "region": "TW",
      "currency": "NT$",
      "price": 395.18,
      "change": 13.22,
      "changePct": 3.46,
      "asOf": "2026-07-22T05:33:00+00:00",
      "source": "TWSE MIS",
      "priceType": "trade"
    },
    {
      "id": "spx",
      "symbol": "^GSPC",
      "name": "S&P 500",
      "region": "US",
      "currency": "$",
      "price": 7498.96,
      "change": -10.24,
      "changePct": -0.14,
      "asOf": "2026-07-22T20:42:14+00:00",
      "source": "Yahoo Finance",
      "priceType": "trade"
    },
    {
      "id": "ndx",
      "symbol": "^IXIC",
      "name": "NASDAQ",
      "region": "US",
      "currency": "$",
      "price": 25690.902,
      "change": -146.3,
      "changePct": -0.57,
      "asOf": "2026-07-22T20:48:31+00:00",
      "source": "Yahoo Finance",
      "priceType": "trade"
    },
    {
      "id": "sox",
      "symbol": "^SOX",
      "name": "費城半導體 SOX",
      "region": "US",
      "currency": "$",
      "price": 12410.665,
      "change": 54.5,
      "changePct": 0.44,
      "asOf": "2026-07-22T20:48:31+00:00",
      "source": "Yahoo Finance",
      "priceType": "trade"
    }
  ]
}
