{
  "timestamp": "2026-07-15T12:17:01.853030+08:00",
  "data": [
    {
      "id": "tai",
      "name": "加權指數 TAIEX",
      "region": "TW",
      "currency": "NT$",
      "price": 45709.05,
      "change": 971.1,
      "changePct": 2.17
    },
    {
      "id": "otc",
      "name": "OTC 櫃買指數",
      "region": "TW",
      "currency": "NT$",
      "price": 416.2,
      "change": 8.79,
      "changePct": 2.16
    },
    {
      "id": "spx",
      "name": "S&P 500",
      "region": "US",
      "currency": "$",
      "price": 7543.59,
      "change": 28.25,
      "changePct": 0.38
    },
    {
      "id": "ndx",
      "name": "NASDAQ",
      "region": "US",
      "currency": "$",
      "price": 26107.008,
      "change": 233.83,
      "changePct": 0.9
    },
    {
      "id": "sox",
      "name": "費城半導體 SOX",
      "region": "US",
      "currency": "$",
      "price": 12661.931,
      "change": 314.15,
      "changePct": 2.54
    }
  ]
}