{
  "timestamp": "2026-07-17T14:04:57.313484+00:00",
  "generatedAt": "2026-07-17T14:04:57.313484+00:00",
  "data": [
    {
      "region": "TW",
      "headline": "貿協攜手北市府領10家台企赴日 拓展AI市場促逾875萬美元潛在商機",
      "source": "鉅亨",
      "time": "--:--",
      "impact": "neu",
      "link": "https://news.cnyes.com/news/id/6538962"
    },
    {
      "region": "TW",
      "headline": "俄烏互襲商船重創糧食出口 全球小麥價格應聲飆漲",
      "source": "鉅亨",
      "time": "--:--",
      "impact": "pos",
      "link": "https://news.cnyes.com/news/id/6538902"
    },
    {
      "region": "TW",
      "headline": "無人機出口破2億美元暴風成長百倍！經濟部盤點自主研發「實績」駁斥政治抹黑",
      "source": "鉅亨",
      "time": "--:--",
      "impact": "neu",
      "link": "https://news.cnyes.com/news/id/6538965"
    },
    {
      "region": "TW",
      "headline": "瞄準數位支付與創新金融！聯邦美國金融創新ETF今掛牌上櫃 追蹤「彭博TPEx」指數",
      "source": "鉅亨",
      "time": "--:--",
      "impact": "neu",
      "link": "https://news.cnyes.com/news/id/6538956"
    },
    {
      "region": "TW",
      "headline": "一卡通總座估7月電支代收付迎強勁反彈 攜應援科技、Flexii打造支付新生態圈",
      "source": "台股",
      "time": "--:--",
      "impact": "neu",
      "link": "https://news.cnyes.com/news/id/6538951"
    }
  ]
}
