{
  "timestamp": "2026-07-08T23:35:22.336367+08:00",
  "data": [
    {
      "region": "TW",
      "headline": "蘋果不敵歐盟！法院駁回DMA挑戰 App Store與iOS仍列守門人",
      "source": "鉅亨",
      "time": "--:--",
      "impact": "neu",
      "link": "https://news.cnyes.com/news/id/6527919"
    },
    {
      "region": "TW",
      "headline": "日本借貸成本飆升至30年新高 債務擔憂與政策轉型引發市場動盪",
      "source": "鉅亨",
      "time": "--:--",
      "impact": "pos",
      "link": "https://news.cnyes.com/news/id/6527734"
    },
    {
      "region": "TW",
      "headline": "比特幣一度跌破6.2萬美元！川普發言引爆伊朗戰火疑慮 加密市場再陷震盪",
      "source": "鉅亨",
      "time": "--:--",
      "impact": "neg",
      "link": "https://news.cnyes.com/news/id/6527953"
    },
    {
      "region": "TW",
      "headline": "精確對華為、長安汽車放量出貨 6月營收衝出新高紀錄",
      "source": "鉅亨",
      "time": "--:--",
      "impact": "neu",
      "link": "https://news.cnyes.com/news/id/6527920"
    },
    {
      "region": "TW",
      "headline": "國發會、櫃買中心與創投公會攜手「陪跑」12家新創Demo Show大秀實力",
      "source": "台股",
      "time": "--:--",
      "impact": "neu",
      "link": "https://news.cnyes.com/news/id/6527925"
    },
    {
      "region": "TW",
      "headline": "商總與日本商總簽MOU 許舒博：未來擴大與全球商總簽約、帶服務業打國家隊",
      "source": "台股",
      "time": "--:--",
      "impact": "neu",
      "link": "https://news.cnyes.com/news/id/6527805"
    },
    {
      "region": "TW",
      "headline": "台股震盪資金轉進ETF避颱 高息題材吸睛 公股大買這10檔搶卡位",
      "source": "台股",
      "time": "--:--",
      "impact": "neu",
      "link": "https://news.cnyes.com/news/id/6527806"
    }
  ]
}