{
  "timestamp": "2026-06-17T12:24:03.752615+08:00",
  "data": [
    {
      "region": "TW",
      "headline": "繼Prime案後再陷監管風暴 亞馬遜恐因誤導廣告主付出代價",
      "source": "鉅亨",
      "time": "--:--",
      "impact": "neu",
      "link": "https://news.cnyes.com/news/id/6502039"
    },
    {
      "region": "TW",
      "headline": "AI智能體將取代APP！高通執行長揭逾40款AI終端設計：重返資料中心CPU 挑戰輝達推理市場",
      "source": "鉅亨",
      "time": "--:--",
      "impact": "neu",
      "link": "https://news.cnyes.com/news/id/6501327"
    },
    {
      "region": "TW",
      "headline": "華許Fed首秀恐缺席「點陣圖」？打破14年慣例 市場緊盯新主席如何改造溝通模式 ",
      "source": "鉅亨",
      "time": "--:--",
      "impact": "neu",
      "link": "https://news.cnyes.com/news/id/6502063"
    },
    {
      "region": "TW",
      "headline": "特斯拉股價難逃SpaceX引力 AI進展成追趕關鍵",
      "source": "鉅亨",
      "time": "--:--",
      "impact": "neu",
      "link": "https://news.cnyes.com/news/id/6502027"
    },
    {
      "region": "TW",
      "headline": "台糖80週年獲利雙亮眼 配息1.3元 攜手林百貨設計紀念品讓股東「呷甜」",
      "source": "台股",
      "time": "--:--",
      "impact": "neu",
      "link": "https://news.cnyes.com/news/id/6501894"
    },
    {
      "region": "TW",
      "headline": "交長開箱桃機三航廈預計2027完工 屆時提供旅客年服務容量4500萬人次",
      "source": "台股",
      "time": "--:--",
      "impact": "neu",
      "link": "https://news.cnyes.com/news/id/6501826"
    },
    {
      "region": "TW",
      "headline": "國發「百億投資平台」偕AI新十大建設吸睛！領軍500餘家共引資破千億",
      "source": "台股",
      "time": "--:--",
      "impact": "neu",
      "link": "https://news.cnyes.com/news/id/6501804"
    },
    {
      "region": "TW",
      "headline": "〈618電商大檔〉品牌GMV年增27% 蝦皮：AI技術驅動成長",
      "source": "台股",
      "time": "--:--",
      "impact": "neu",
      "link": "https://news.cnyes.com/news/id/6501796"
    }
  ]
}