{
  "timestamp": "2026-06-26T16:22:12.365491+08:00",
  "data": [
    {
      "region": "TW",
      "headline": "〈台電股東會〉中止連3年虧損！去年轉盈756億 估今年虧損收歛至280億元內",
      "source": "鉅亨",
      "time": "--:--",
      "impact": "neu",
      "link": "https://news.cnyes.com/news/id/6513586"
    },
    {
      "region": "TW",
      "headline": "香港房價連漲12個月 創7年最長連漲紀錄 租金同步刷新紀錄",
      "source": "鉅亨",
      "time": "--:--",
      "impact": "pos",
      "link": "https://news.cnyes.com/news/id/6513391"
    },
    {
      "region": "TW",
      "headline": "〈北基股東會〉通過配息0.3元 未來多元布局能源、土建強化營運成長動能",
      "source": "鉅亨",
      "time": "--:--",
      "impact": "neu",
      "link": "https://news.cnyes.com/news/id/6513596"
    },
    {
      "region": "TW",
      "headline": "〈房產〉房貸償還期越拉越長 新北及新竹市10年間增長88期",
      "source": "鉅亨",
      "time": "--:--",
      "impact": "neu",
      "link": "https://news.cnyes.com/news/id/6513655"
    },
    {
      "region": "TW",
      "headline": "鉅亨速報 - Factset 最新調查：東陽(1319-TW)EPS預估下修至6.54元，預估目標價為105元",
      "source": "台股",
      "time": "--:--",
      "impact": "neg",
      "link": "https://news.cnyes.com/news/id/6513747"
    },
    {
      "region": "TW",
      "headline": "鉅亨速報 - Factset 最新調查：藥華藥(6446-TW)EPS預估上修至25.72元，預估目標價為1041.5元",
      "source": "台股",
      "time": "--:--",
      "impact": "neu",
      "link": "https://news.cnyes.com/news/id/6513746"
    },
    {
      "region": "TW",
      "headline": "鉅亨速報 - Factset 最新調查：元大金(2885-TW)目標價調升至55.95元，幅度約11.9%",
      "source": "台股",
      "time": "--:--",
      "impact": "neu",
      "link": "https://news.cnyes.com/news/id/6513744"
    }
  ]
}